AUTHORS
ChangeLog
LICENSE
README.rst
requirements-conda.txt
requirements.txt
setup.cfg
setup.py
test.py
doc/conf.py
doc/index.rst
doc/api/green.rst
doc/api/index.rst
doc/api/linop.rst
doc/api/meshes.rst
doc/general/install.rst
doc/images/pycsou.png
doc/notes/index.rst
doc/notes/references.rst
pycsphere/__init__.py
pycsphere/green.py
pycsphere/linop.py
pycsphere/mesh.py
pycsphere.egg-info/PKG-INFO
pycsphere.egg-info/SOURCES.txt
pycsphere.egg-info/dependency_links.txt
pycsphere.egg-info/pbr.json
pycsphere.egg-info/requires.txt
pycsphere.egg-info/top_level.txt
pycsphere.egg-info/zip-safe