Metadata-Version: 2.1
Name: pycsphere
Version: 1.0.0
Summary: Pycsou extension module for spherical inverse problems.
Home-page: https://github.com/matthieumeo/pycsou-sphere
Author: Matthieu SIMEONI
Author-email: matthieu.simeoni@gmail.com
License: MIT
Download-URL: https://github.com/matthieumeo/pycsou-sphere
Platform: UNKNOWN
Classifier: Development Status :: 5 - Production/Stable
Classifier: Intended Audience :: Science/Research
Classifier: License :: OSI Approved :: MIT License
Classifier: Programming Language :: Python :: 3
Classifier: Programming Language :: Python :: Implementation :: CPython
Classifier: Topic :: Scientific/Engineering
Requires-Python: >=3.6
